exampleapp2/__init__.py
exampleapp2/divide/__init__.py
exampleapp2/divide/divide_by_three.py
exampleapp2/multiply/__init__.py
exampleapp2/multiply/multiply_by_three.py
exampleapp2-0.0.12.dist-info/AUTHORS
exampleapp2-0.0.12.dist-info/LICENCE
exampleapp2-0.0.12.dist-info/METADATA
exampleapp2-0.0.12.dist-info/WHEEL
exampleapp2-0.0.12.dist-info/top_level.txt
exampleapp2-0.0.12.dist-info/RECORD
