Metadata-Version: 2.1
Name: exampleapp2
Version: 0.0.12
Summary: short package description
Author: author
Author-email: author@example.com
Project-URL: Bug Tracker, https://code.exampleapp.com/
Project-URL: Documentation, https://docs.exampleapp.com/
Project-URL: Release notes, https://docs.exampleapp.com/en/stable/releases/
Project-URL: Funding, https://www.exampleapp.com/fundraising/
Project-URL: Source, https://github.com/exampleapp/exampleapp
Classifier: Development Status :: 2 - Pre-Alpha
Classifier: Environment :: Web Environment
Classifier: Intended Audience :: Developers
Classifier: Programming Language :: Python :: 3
Classifier: License :: OSI Approved :: MIT License
Classifier: Operating System :: OS Independent
Requires-Python: >=3.7
License-File: LICENCE
License-File: AUTHORS
